luno/__init__.py
luno/decorators.py
luno/exceptions.py
luno/clients/__init__.py
luno/clients/abc.py
luno/clients/async.py
luno/clients/sync.py
luno-0.3.5.dist-info/DESCRIPTION.rst
luno-0.3.5.dist-info/METADATA
luno-0.3.5.dist-info/RECORD
luno-0.3.5.dist-info/WHEEL
luno-0.3.5.dist-info/metadata.json
luno-0.3.5.dist-info/top_level.txt
